Iris_assign_2/Question_2/axi_ram.v
/// use this module to create a RAM with AXI-Stream interface
/// you are allowed to change the input interface to axi-lite if you want


module axi_ram (

    input aclk,
    input aresetn,

    // AXI-Stream Slave

    input [31:0]s_axis_tdata,
    input s_axis_tvalid,
    output reg s_axis_tready,

    // AXI-Stream Master 

    output reg [31:0]m_axis_tdata,
    output reg m_axis_tvalid,
    input m_axis_tready
    
);
reg [7:0] wr_ptr, rd_ptr;
integer count;
reg [7:0] pointer;
reg [7:0] mem [0:288];
// reg valid [0:288];
// integer pointer=0;
always @(posedge aclk) begin
    if(!aresetn) begin
        m_axis_tdata<=0;
        m_axis_tvalid<=0;
        rd_ptr<=0;
    end
    else begin
            
        if(m_axis_tready) begin
            m_axis_tdata<={24'd0, mem[rd_ptr]};
            m_axis_tvalid<=1;
            rd_ptr=(rd_ptr+8'b1)%289;
            // valid[rd_ptr]<=0;
            count=count-1;
        end
        else begin
            m_axis_tdata<=0;
            m_axis_tvalid<=0;
        end
    end
end
wire [8:0]full;
assign full=count;
always @(posedge aclk) begin
    if(!aresetn) begin
        s_axis_tready<=0;
        count<=0;
    end
    else begin
        s_axis_tready<=(count<289);
        if(s_axis_tvalid && full<=9'd288) begin
            mem[s_axis_tdata[23:16]]<=s_axis_tdata[7:0];
            mem[s_axis_tdata[29:25]]<=s_axis_tdata[12:8];
            count<=count+1;
            // valid[s_axis_tdata[23:16]]<=1;
        end
    end
end
endmodule

Iris_assign_2/Question_2/s_m_hist.v
//////////////////////////////////////////////////////////////////////////////////////////////////
////      Edit to create a block to create a data processing block, which takes in data //////////
/// from the lfsr through a AXI-Stream slave interface, and categorises them into bins  //////////
/////      The output data includes the  count value of numbers in each bin and data    //////////
////     + address in ram , which the data is supposed to be written to as provided in  //////////
////                            the address map below                                   //////////
////     The output data is to sent out through a AXI-Stream master/AXI-Lite interface.    ///////
//////////////////////////////////////////////////////////////////////////////////////////////////


//  -------------------------------------------------
//  | Bin Number |    Range of Values               |
//  -------------------------------------------------
//  | Bin 0      |        1   -  32                 |
//  | Bin 1      |       33   -  64                 |
//  | Bin 2      |       65   -  96                 |
//  | Bin 3      |       97   - 128                 |
//  | Bin 4      |      129   - 160                 |
//  | Bin 5      |      161   - 192                 |
//  | Bin 6      |      193   - 224                 |
//  | Bin 7      |      225   - 255                 |
//  -------------------------------------------------


// assume the ram to be 0x120 x 8 bit 

// ----------------------------------------------------------------------------------------
// | Address Range      | Register / Memory     | Description                              |
// ----------------------------------------------------------------------------------------
// | 0x00              | Bin 0 Count           | Count for values in range 1-32           |
// | 0x04              | Bin 1 Count           | Count for values in range 33-64          |
// | 0x08              | Bin 2 Count           | Count for values in range 65-96          |
// | 0x0C              | Bin 3 Count           | Count for values in range 97-128         |
// | 0x10              | Bin 4 Count           | Count for values in range 129-160        |
// | 0x14              | Bin 5 Count           | Count for values in range 161-192        |
// | 0x18              | Bin 6 Count           | Count for values in range 193-224        |
// | 0x1C              | Bin 7 Count           | Count for values in range 225-255        |
// ----------------------------------------------------------------------------------------
// | 0x20 - 0x3F       | Bin 0 Data Storage    | Stores values belonging to Bin 0         |
// | 0x40 - 0x5F       | Bin 1 Data Storage    | Stores values belonging to Bin 1         |
// | 0x60 - 0x7F       | Bin 2 Data Storage    | Stores values belonging to Bin 2         |
// | 0x80 - 0x9F       | Bin 3 Data Storage    | Stores values belonging to Bin 3         |
// | 0xA0 - 0xBF       | Bin 4 Data Storage    | Stores values belonging to Bin 4         |
// | 0xC0 - 0xDF       | Bin 5 Data Storage    | Stores values belonging to Bin 5         |
// | 0xE0 - 0xFF       | Bin 6 Data Storage    | Stores values belonging to Bin 6         |
// | 0x100 - 0x11F     | Bin 7 Data Storage    | Stores values belonging to Bin 7         |
// ----------------------------------------------------------------------------------------





module s_m_hist (

    input aclk,
    input aresetn,

    // AXI-Stream Slave

    input [31:0]s_axis_tdata,
    input s_axis_tvalid,
    output reg s_axis_tready,

    // AXI-Stream Master 

    output reg [31:0]m_axis_tdata,
    output reg m_axis_tvalid,
    input wire m_axis_tready
    
);
    reg [31:0]s_final_tdata;
    reg [4:0] count[7:0];
    always @(*) begin
        if(!aresetn) begin
            count[0] = 8'd0;
            count[1] = 8'd0;
            count[2] = 8'd0;
            count[3] = 8'd0;
            count[4] = 8'd0;
            count[5] = 8'd0;
            count[6] = 8'd0;
            count[7] = 8'd0;
        end
        else begin

            // if(!m_axis_tvalid && m_axis_tready) begin
            //     s_axis_tready <= 1'b1;
            // end

            // else s_axis_tready <= 1'b0;

            if(s_axis_tdata<=32'd32 && s_axis_tdata>=32'd1) begin
                count[0]=count[0]+5'd1;
                s_final_tdata={5'd0,5'd0,9'h20 + count[0]-8'd1,count[0],s_axis_tdata[7:0]};
            end
            else if (s_axis_tdata<=32'd64 && s_axis_tdata>=32'd33) begin
                count[1]=count[1]+5'd1;
                s_final_tdata={5'd0,5'd4,9'h40 + count[1]-8'd1,count[1],s_axis_tdata[7:0]};
            end
            else if (s_axis_tdata<=32'd96 && s_axis_tdata>=32'd65) begin
                count[2]=count[2]+5'd1;
                s_final_tdata={5'd0,5'd8,9'h60 + count[2]-8'd1,count[2],s_axis_tdata[7:0]};
            end
            else if (s_axis_tdata<=32'd128 && s_axis_tdata>=32'd97) begin
                count[3]=count[3]+5'd1;
                s_final_tdata={5'd0, 5'hc, 9'h80 + count[3]-8'd1,count[3],s_axis_tdata[7:0]};
            end
            else if (s_axis_tdata<=32'd160 && s_axis_tdata>=32'd129) begin
                count[4]=count[4]+5'd1;
                s_final_tdata={5'd0,5'h10,9'ha0 + count[4]-8'd1,count[4],s_axis_tdata[7:0]};
            end
            else if (s_axis_tdata<=32'd192 && s_axis_tdata>=32'd161) begin
                count[5]=count[5]+5'd1;
                s_final_tdata={5'd0,5'h14,9'hc0 + count[5]-8'd1,count[5],s_axis_tdata[7:0]};
            end
            else if (s_axis_tdata<=32'd224 && s_axis_tdata>=32'd193) begin
                count[6]=count[6]+5'd1;
                s_final_tdata={5'd0,5'h18,9'he0 + count[6]-8'd1,count[6],s_axis_tdata[7:0]};
            end
            else if (s_axis_tdata<=32'd255 && s_axis_tdata>=32'd225) begin
                count[7]=count[7]+5'd1;
                s_final_tdata={5'd0,5'h1c,9'h100 + count[7]-8'd1,count[7],s_axis_tdata[7:0]};
            end
        end
    end

    always @(posedge aclk) begin

        if(!aresetn) begin
            s_axis_tready<=0;
            m_axis_tvalid<=0;
            m_axis_tdata<=0;
        end

        else begin

            // s_axis_tready<=1;

            if(!m_axis_tvalid && m_axis_tready) begin

                s_axis_tready<=1;

                if(s_axis_tvalid && m_axis_tready) begin
                    m_axis_tdata<=s_final_tdata;
                    m_axis_tvalid<=1;
                end

                else begin
                    m_axis_tvalid<=0;
                end
            end

            else begin
                m_axis_tvalid<=0;
                s_axis_tready <= 1'b0;
            end
        end
    end
endmodule

Iris_assign_2/Question_2/saxl_lfsr.v
//////////////////////////////////////////////////////////////////////////////////
////      Edit to create a 8bit LFSR module with AXI-Lite interface          /////
/////      for register configuration and AX-Stream for lfsr output          /////
//////////////////////////////////////////////////////////////////////////////////


module s_axil #(
    parameter C_AXIL_ADDR_WIDTH = 4,
    parameter C_AXIL_DATA_WIDTH = 32
)(
    input aclk,
    input aresetn,

    // AXI-Lite Slave Interface
    input  [C_AXIL_ADDR_WIDTH-1:0] s_axi_awaddr,
    input                       s_axi_awvalid,
    output reg                  s_axi_awready,

    input  [C_AXIL_DATA_WIDTH-1:0] s_axi_wdata,
    input                       s_axi_wvalid,
    output reg                  s_axi_wready,

    output reg [1:0]            s_axi_bresp,
    output reg                  s_axi_bvalid,
    input                       s_axi_bready,

    // read starts

    input  [C_AXIL_ADDR_WIDTH-1:0] s_axi_araddr,
    input                       s_axi_arvalid,
    output reg                  s_axi_arready,

    output reg [C_AXIL_DATA_WIDTH-1:0] s_axi_rdata,
    output reg [1:0]            s_axi_rresp,
    output reg                  s_axi_rvalid,
    input                       s_axi_rready,

    // AXI - Stream Master Interface
    output reg [C_AXIL_DATA_WIDTH-1:0] m_axis_tdata,
    output reg                    m_axis_tvalid,
    input         wire                m_axis_tready
);


    //Address map for these registers

    // 0x00 - start_reg
    // 0x04 - stop_reg
    // 0x08 - seed_reg
    // 0x0C - taps_reg

    // Registers
    reg start_reg;
    reg stop_reg;
    reg [7:0] seed_reg;
    reg [7:0] taps_reg;
    reg [31:0] last_lfsr_val;
    reg lfsr_tvalid;
    reg [7:0] lfsr_tdata;

    // for write slave
    always @(posedge aclk) begin
        if(!aresetn) begin
            s_axi_awready<=0;
            s_axi_wready<=0;
        end
        else begin
            if(s_axi_awvalid && s_axi_wvalid && !s_axi_awready && !s_axi_wready) begin
                s_axi_awready<=1;
                s_axi_wready<=1;
                case (s_axi_awaddr)
                    4'b0: begin
                        start_reg<=1;
                        // stop_reg<=0;
                        end
                    4'h4:begin 
                        stop_reg<=s_axi_wdata[0];
                        // start_reg<=0;
                        end
                    4'h8: seed_reg<=s_axi_wdata[7:0];
                    4'hc: taps_reg<=s_axi_wdata[7:0];
                endcase;
                s_axi_bresp<=2'd0;
                s_axi_bvalid<=1;
            end
            if(s_axi_awvalid && s_axi_wvalid && s_axi_awready && s_axi_wready) begin
                s_axi_bresp<=2'd0;
                s_axi_bvalid<=1;
            end               
            else if(s_axi_awready & s_axi_wready) begin
                s_axi_awready<=0;
                s_axi_wready<=0;
            end
            if(s_axi_bready) s_axi_bvalid<=0;

            
        end
    end
    always @(posedge aclk) begin
        if(!aresetn) begin
            s_axi_arready<=0;
            s_axi_rdata<=0;
            s_axi_rresp<=0;
            s_axi_rvalid<=0;
            // s_axi_rready<=0;
        end
        else begin
            if(s_axi_arvalid && !s_axi_arready && !s_axi_rresp && !s_axi_rvalid) begin
                s_axi_arready<=1;
                s_axi_rresp<=2'd0;
                s_axi_rvalid<=1;
                case (s_axi_awaddr)
                    4'b0: begin
                        s_axi_rdata={31'd0,start_reg};
                        // stop_reg<=0;
                        end
                    4'd4:begin 
                        s_axi_rdata={31'd0,stop_reg};
                        // start_reg<=0;
                        end
                    4'd8:s_axi_rdata={24'd0,seed_reg[7:0]};
                    4'hc:s_axi_rdata={24'd0,taps_reg[7:0]};
                endcase;
            end
            else if(s_axi_arready && s_axi_rvalid) begin
                s_axi_arready<=0;
                s_axi_rresp<=0;
                s_axi_rvalid<=0;
            end
        end

    end
    always @(*) begin
        if(!aresetn) begin
            lfsr_tvalid=0;
            // m_axis_tready<=0;
            lfsr_tdata=8'd0;
            stop_reg<=0;
        end
        else begin
            if(stop_reg) begin 
                lfsr_tdata=lfsr_tdata;
                lfsr_tvalid=0;
            end
            else if(start_reg) begin
                if(!lfsr_tvalid) begin
                    lfsr_tdata={seed_reg};
                    lfsr_tvalid=1;
                end
                else if(m_axis_tready && lfsr_tvalid) begin
                    lfsr_tdata={lfsr_tdata[6:0],^(taps_reg&lfsr_tdata)};
                end

            end
        end
    end
    always @ (posedge aclk) begin
        if(!aresetn) begin
            m_axis_tdata<=0;
            m_axis_tvalid<=0;
        end
        else begin
            m_axis_tvalid<=lfsr_tvalid;
            m_axis_tdata<={24'b0,lfsr_tdata};
        end
    end



endmodule;

Iris_assign_2/Question_2/lfsr_core.v
`include "saxl_lfsr.v"
`include "s_m_hist.v"
`include "axi_ram.v"




module core(
    input aclk,
    input aresetn,
    input wire [C_AXIL_ADDR_WIDTH-1:0] lfsr_s_axi_awaddr,
    input wire lfsr_s_axi_awvalid, 
    output wire lfsr_s_axi_awready,
    input wire [C_AXIL_DATA_WIDTH-1:0] lfsr_s_axi_wdata,
    input wire lfsr_s_axi_wvalid, 
    output wire lfsr_s_axi_wready,
    input wire [C_AXIL_ADDR_WIDTH-1:0] lfsr_s_axi_araddr,
    input wire lfsr_s_axi_arvalid,
    output lfsr_s_axi_arready,
    output wire [1:0] lfsr_s_axi_rresp,
    output wire [1:0] lfsr_s_axi_bresp,
    output wire lfsr_s_axi_bvalid, 
    input wire lfsr_s_axi_bready,
    output wire lfsr_s_axi_rvalid,
    input wire  lfsr_s_axi_rready,
    output wire [C_AXIL_DATA_WIDTH-1:0] lfsr_s_axi_rdata,
    output wire [C_AXIL_DATA_WIDTH-1:0] lfsr_m_axis_tdata,
    output wire lfsr_m_axis_tvalid

);
    parameter C_AXIL_ADDR_WIDTH = 4;
    parameter C_AXIL_DATA_WIDTH = 32;
    wire lfsr_m_axis_tready;
    // wire [C_AXIL_ADDR_WIDTH-1:0] lfsr_s_axi_awaddr;
    // wire lfsr_s_axi_awvalid, lfsr_s_axi_awready;
    // wire [C_AXIL_DATA_WIDTH-1:0] lfsr_s_axi_wdata;
    // wire lfsr_s_axi_wvalid, lfsr_s_axi_wready;
    // wire [C_AXIL_ADDR_WIDTH-1:0] lfsr_s_axi_araddr;
    // wire lfsr_s_axi_arvalid, lfsr_s_axi_arready;
    // wire [1:0] lfsr_s_axi_rresp;
    // wire [1:0] lfsr_s_axi_bresp;
    // wire lfsr_s_axi_bvalid, lfsr_s_axi_bready;
    // wire lfsr_s_axi_rvalid, lfsr_s_axi_rready;
    // wire [C_AXIL_DATA_WIDTH-1:0] lfsr_s_axi_rdata;
    // wire [C_AXIL_DATA_WIDTH-1:0] lfsr_m_axis_tdata;
    // wire lfsr_m_axis_tvalid, lfsr_m_axis_tready;

    // histogram
    wire [31:0] hist_m_axis_tdata;
    wire hist_m_axis_tvalid, hist_m_axis_tready;

    // RAM
    wire [31:0] ram_m_axis_tdata;
    wire ram_m_axis_tvalid, ram_m_axis_tready;

    s_axil u_lfsr_axil(
        .aclk(aclk),
        .aresetn(aresetn),
        .s_axi_awaddr(lfsr_s_axi_awaddr),
        .s_axi_awvalid(lfsr_s_axi_awvalid),
        .s_axi_awready(lfsr_s_axi_awready),
        .s_axi_wdata(lfsr_s_axi_wdata),
        .s_axi_wvalid(lfsr_s_axi_wvalid),
        .s_axi_wready(lfsr_s_axi_wready),
        .s_axi_bresp(lfsr_s_axi_bresp),
        .s_axi_bvalid(lfsr_s_axi_bvalid),
        .s_axi_bready(lfsr_s_axi_bready),
        .s_axi_araddr(lfsr_s_axi_araddr),
        .s_axi_arvalid(lfsr_s_axi_arvalid),
        .s_axi_arready(lfsr_s_axi_arready),
        .s_axi_rdata(lfsr_s_axi_rdata),
        .s_axi_rresp(lfsr_s_axi_rresp),
        .s_axi_rvalid(lfsr_s_axi_rvalid),
        .s_axi_rready(lfsr_s_axi_rready),
        .m_axis_tdata(lfsr_m_axis_tdata),
        .m_axis_tvalid(lfsr_m_axis_tvalid),
        .m_axis_tready(lfsr_m_axis_tready)
    );

    s_m_hist s1(
        .aclk(aclk),
        .aresetn(aresetn),
        .s_axis_tdata(lfsr_m_axis_tdata),
        .s_axis_tvalid(lfsr_m_axis_tvalid),
        .s_axis_tready(lfsr_m_axis_tready),
        .m_axis_tdata(hist_m_axis_tdata),
        .m_axis_tvalid(hist_m_axis_tvalid),
        .m_axis_tready(hist_m_axis_tready)
    );

    axi_ram a0(
        .aclk(aclk),
        .aresetn(aresetn),
        .s_axis_tdata(hist_m_axis_tdata),
        .s_axis_tvalid(hist_m_axis_tvalid),
        .s_axis_tready(hist_m_axis_tready),
        .m_axis_tdata(ram_m_axis_tdata),
        .m_axis_tvalid(ram_m_axis_tvalid),
        .m_axis_tready(ram_m_axis_tready)
    );

endmodule

Iris_assign_2/Question_2/new_tb.v
`include "lfsr_core.v"

`timescale 1ns/1ns

module tb_top_level;


core dut (
    .aclk(aclk),
    .aresetn(aresetn),

    // AXI Write Address Channel
    .lfsr_s_axi_awaddr(lfsr_s_axi_awaddr),
    .lfsr_s_axi_awvalid(lfsr_s_axi_awvalid),
    .lfsr_s_axi_awready(lfsr_s_axi_awready),

    // AXI Write Data Channel
    .lfsr_s_axi_wdata(lfsr_s_axi_wdata),
    .lfsr_s_axi_wvalid(lfsr_s_axi_wvalid),
    .lfsr_s_axi_wready(lfsr_s_axi_wready),

    // AXI Read Address Channel
    .lfsr_s_axi_araddr(lfsr_s_axi_araddr),
    .lfsr_s_axi_arvalid(lfsr_s_axi_arvalid),
    .lfsr_s_axi_arready(lfsr_s_axi_arready),

    // AXI Read Data Channel
    .lfsr_s_axi_rresp(lfsr_s_axi_rresp),
    .lfsr_s_axi_rvalid(lfsr_s_axi_rvalid),
    .lfsr_s_axi_rready(lfsr_s_axi_rready),
    .lfsr_s_axi_rdata(lfsr_s_axi_rdata),

    // AXI Write Response Channel
    .lfsr_s_axi_bresp(lfsr_s_axi_bresp),
    .lfsr_s_axi_bvalid(lfsr_s_axi_bvalid),
    .lfsr_s_axi_bready(lfsr_s_axi_bready),

    // LFSR Output Stream
    .lfsr_m_axis_tdata(lfsr_m_axis_tdata),
    .lfsr_m_axis_tvalid(lfsr_m_axis_tvalid)
);

        // LFSR Interface Signals
    reg aclk, aresetn;
    reg [3:0]  lfsr_s_axi_awaddr;
    reg        lfsr_s_axi_awvalid;
    wire       lfsr_s_axi_awready;
    reg [31:0] lfsr_s_axi_wdata;
    reg        lfsr_s_axi_wvalid;
    wire       lfsr_s_axi_wready;
    reg [3:0]  lfsr_s_axi_araddr;
    reg        lfsr_s_axi_arvalid;
    wire       lfsr_s_axi_arready;
    wire [1:0] lfsr_s_axi_rresp;
    wire [1:0] lfsr_s_axi_bresp;
    wire       lfsr_s_axi_bvalid;
    reg        lfsr_s_axi_bready;
    wire       lfsr_s_axi_rvalid;
    reg        lfsr_s_axi_rready;
    wire [31:0] lfsr_s_axi_rdata;

    // LFSR Data Stream
    wire [31:0] lfsr_m_axis_tdata;
    wire        lfsr_m_axis_tvalid;
    reg         lfsr_m_axis_tready;

    // Histogram Output
    wire [31:0] hist_m_axis_tdata;
    wire        hist_m_axis_tvalid;
    reg         hist_m_axis_tready;

    // RAM Output
    wire [31:0] ram_m_axis_tdata;
    wire        ram_m_axis_tvalid;
    reg         ram_m_axis_tready;

    initial begin
        aclk = 1'b0;
        forever #5 aclk = ~aclk;
    end

    initial begin
        aresetn = 1'b0;
        #20;        
        aresetn = 1'b1;
    end

    initial begin
        lfsr_s_axi_awaddr  = 4'h0;
        lfsr_s_axi_awvalid = 1'b0;
        lfsr_s_axi_wdata   = 32'd0;
        lfsr_s_axi_wvalid  = 1'b0;
        lfsr_s_axi_bready  = 1'b0;

        lfsr_s_axi_araddr  = 4'h0;
        lfsr_s_axi_arvalid = 1'b0;
        lfsr_s_axi_rready  = 1'b0;
    end

    //------------------------------------------------------------------------------
    //  AXI-Lite Write Task
    //------------------------------------------------------------------------------
    task axi_lite_write(
        input [3:0]  addr,
        input [31:0] data
    );
    begin
        // Address phase
        lfsr_s_axi_awaddr  <= addr;
        lfsr_s_axi_awvalid <= 1'b1;
        // Data phase
        lfsr_s_axi_wdata   <= data;
        lfsr_s_axi_wvalid  <= 1'b1;

        // Wait until AW and W are accepted
        @(posedge aclk);
        while(!(lfsr_s_axi_awready && lfsr_s_axi_awvalid && lfsr_s_axi_wready && lfsr_s_axi_wvalid)) begin
            @(posedge aclk);
        end

        // Deassert
        lfsr_s_axi_awvalid <= 1'b0;
        lfsr_s_axi_wvalid  <= 1'b0;

        // Wait for BVALID
        @(posedge aclk);
        while(!lfsr_s_axi_bvalid) begin
            @(posedge aclk);
        end

        // Ack the response
        lfsr_s_axi_bready <= 1'b1;
        @(posedge aclk);
        lfsr_s_axi_bready <= 1'b0;
    end
    endtask

    //------------------------------------------------------------------------------
    //  AXI-Lite Read Task
    //------------------------------------------------------------------------------
    task axi_lite_read(
        input  [3:0]  addr,
        output [31:0] data_out
    );
    begin
        lfsr_s_axi_araddr  <= addr;
        lfsr_s_axi_arvalid <= 1'b1;

        // Wait for AR to be accepted
        @(posedge aclk);
        while(!(lfsr_s_axi_awready && lfsr_s_axi_arvalid)) begin
            @(posedge aclk);
        end
        lfsr_s_axi_arvalid <= 1'b0;

        // Wait for RVALID
        @(posedge aclk);
        while(!lfsr_s_axi_rvalid) begin
            @(posedge aclk);
        end
        data_out      = lfsr_s_axi_rdata;

        // Ack
        lfsr_s_axi_rready <= 1'b1;
        @(posedge aclk);
        lfsr_s_axi_rready <= 1'b0;
    end
    endtask

    //------------------------------------------------------------------------------
    //  Test Sequence
    //------------------------------------------------------------------------------
    initial begin
        // Wait for reset
        @(posedge aresetn);
        @(posedge aclk);

        $display("INFO: Configuring lfsr through AXI-Lite...");

        // Example writes:
        // Write seed_reg @0x08 = 8'hAC
        axi_lite_write(4'h8, 32'h000000AC);

        // Write taps_reg @0x0C = 8'hA2
        axi_lite_write(4'hC, 32'h000000A2);

        // Write stop_reg @0x04 = 0
        axi_lite_write(4'h4, 32'h0);

        // Write start_reg @0x00 = 1
        axi_lite_write(4'h0, 32'h1);

        $display("LFSR has started.");
        // $display("Time=%0t,aw_valid=%b, w_valid=%b start_reg=%b, stop_reg=%b, seed_reg=%h, taps_reg=%h, lfsr_reg=%h",
        //   $time,
        //   dut.u_lfsr_axil.start_reg,lfsr_s_axi_awvalid,lfsr_s_axi_wvalid, dut.u_lfsr_axil.stop_reg, dut.u_lfsr_axil.seed_reg, dut.u_lfsr_axil.taps_reg, dut.u_lfsr_axil.lfsr_tdata);

        $monitor("Time=%0t,aw_valid=%b, w_valid=%b start_reg=%b, stop_reg=%b, seed_reg=%h, taps_reg=%h, lfsr_reg=%h",
          $time,
          dut.u_lfsr_axil.start_reg,lfsr_s_axi_awvalid,lfsr_s_axi_wvalid, dut.u_lfsr_axil.stop_reg, dut.u_lfsr_axil.seed_reg, dut.u_lfsr_axil.taps_reg, dut.u_lfsr_axil.lfsr_tdata);


        // Let the design run for a while
        repeat(300) @(posedge aclk);

        $display("INFO: Simulation done. Check waveforms / logs to see memory writes.");
        $finish;
    end

    
    //------------------------------------------------------------------------------
    //  (Optional) Waveform Dump
    //------------------------------------------------------------------------------
    initial begin
        // VCD file name can be anything you like
        $dumpfile("tb_top_level.vcd");
        // 0 means dump everything in the hierarchy
        $dumpvars(0, tb_top_level);
    end

endmodule

Iris_assign_2/Question_2/tb_top_level.vcd
$date
	Thu Apr 03 19:15:54 2025
$end
$version
	Icarus Verilog
$end
$timescale
	1ns
$end
$scope module tb_top_level $end
$var wire 1 ! lfsr_s_axi_wready $end
$var wire 1 " lfsr_s_axi_rvalid $end
$var wire 2 # lfsr_s_axi_rresp [1:0] $end
$var wire 32 $ lfsr_s_axi_rdata [31:0] $end
$var wire 1 % lfsr_s_axi_bvalid $end
$var wire 2 & lfsr_s_axi_bresp [1:0] $end
$var wire 1 ' lfsr_s_axi_awready $end
$var wire 1 ( lfsr_s_axi_arready $end
$var wire 1 ) lfsr_m_axis_tvalid $end
$var wire 32 * lfsr_m_axis_tdata [31:0] $end
$var reg 1 + aclk $end
$var reg 1 , aresetn $end
$var reg 4 - lfsr_s_axi_araddr [3:0] $end
$var reg 1 . lfsr_s_axi_arvalid $end
$var reg 4 / lfsr_s_axi_awaddr [3:0] $end
$var reg 1 0 lfsr_s_axi_awvalid $end
$var reg 1 1 lfsr_s_axi_bready $end
$var reg 1 2 lfsr_s_axi_rready $end
$var reg 32 3 lfsr_s_axi_wdata [31:0] $end
$var reg 1 4 lfsr_s_axi_wvalid $end
$scope module dut $end
$var wire 1 + aclk $end
$var wire 1 , aresetn $end
$var wire 4 5 lfsr_s_axi_araddr [3:0] $end
$var wire 1 . lfsr_s_axi_arvalid $end
$var wire 4 6 lfsr_s_axi_awaddr [3:0] $end
$var wire 1 0 lfsr_s_axi_awvalid $end
$var wire 1 1 lfsr_s_axi_bready $end
$var wire 1 2 lfsr_s_axi_rready $end
$var wire 32 7 lfsr_s_axi_wdata [31:0] $end
$var wire 1 4 lfsr_s_axi_wvalid $end
$var wire 1 8 ram_m_axis_tready $end
$var wire 1 9 ram_m_axis_tvalid $end
$var wire 32 : ram_m_axis_tdata [31:0] $end
$var wire 1 ! lfsr_s_axi_wready $end
$var wire 1 " lfsr_s_axi_rvalid $end
$var wire 2 ; lfsr_s_axi_rresp [1:0] $end
$var wire 32 < lfsr_s_axi_rdata [31:0] $end
$var wire 1 % lfsr_s_axi_bvalid $end
$var wire 2 = lfsr_s_axi_bresp [1:0] $end
$var wire 1 ' lfsr_s_axi_awready $end
$var wire 1 ( lfsr_s_axi_arready $end
$var wire 1 ) lfsr_m_axis_tvalid $end
$var wire 1 > lfsr_m_axis_tready $end
$var wire 32 ? lfsr_m_axis_tdata [31:0] $end
$var wire 1 @ hist_m_axis_tvalid $end
$var wire 1 A hist_m_axis_tready $end
$var wire 32 B hist_m_axis_tdata [31:0] $end
$scope module a0 $end
$var wire 1 + aclk $end
$var wire 1 , aresetn $end
$var wire 1 8 m_axis_tready $end
$var wire 1 @ s_axis_tvalid $end
$var wire 32 C s_axis_tdata [31:0] $end
$var wire 9 D full [8:0] $end
$var reg 32 E m_axis_tdata [31:0] $end
$var reg 1 9 m_axis_tvalid $end
$var reg 8 F rd_ptr [7:0] $end
$var reg 1 A s_axis_tready $end
$var integer 32 G count [31:0] $end
$upscope $end
$scope module s1 $end
$var wire 1 + aclk $end
$var wire 1 , aresetn $end
$var wire 1 A m_axis_tready $end
$var wire 1 ) s_axis_tvalid $end
$var wire 32 H s_axis_tdata [31:0] $end
$var reg 32 I m_axis_tdata [31:0] $end
$var reg 1 @ m_axis_tvalid $end
$var reg 1 > s_axis_tready $end
$var reg 32 J s_final_tdata [31:0] $end
$upscope $end
$scope module u_lfsr_axil $end
$var wire 1 + aclk $end
$var wire 1 , aresetn $end
$var wire 1 > m_axis_tready $end
$var wire 4 K s_axi_araddr [3:0] $end
$var wire 1 . s_axi_arvalid $end
$var wire 4 L s_axi_awaddr [3:0] $end
$var wire 1 0 s_axi_awvalid $end
$var wire 1 1 s_axi_bready $end
$var wire 1 2 s_axi_rready $end
$var wire 32 M s_axi_wdata [31:0] $end
$var wire 1 4 s_axi_wvalid $end
$var reg 8 N lfsr_tdata [7:0] $end
$var reg 1 O lfsr_tvalid $end
$var reg 32 P m_axis_tdata [31:0] $end
$var reg 1 ) m_axis_tvalid $end
$var reg 1 ( s_axi_arready $end
$var reg 1 ' s_axi_awready $end
$var reg 2 Q s_axi_bresp [1:0] $end
$var reg 1 % s_axi_bvalid $end
$var reg 32 R s_axi_rdata [31:0] $end
$var reg 2 S s_axi_rresp [1:0] $end
$var reg 1 " s_axi_rvalid $end
$var reg 1 ! s_axi_wready $end
$var reg 8 T seed_reg [7:0] $end
$var reg 1 U start_reg $end
$var reg 1 V stop_reg $end
$var reg 8 W taps_reg [7:0] $end
$upscope $end
$upscope $end
$scope task axi_lite_read $end
$var reg 4 X addr [3:0] $end
$var reg 32 Y data_out [31:0] $end
$upscope $end
$scope task axi_lite_write $end
$var reg 4 Z addr [3:0] $end
$var reg 32 [ data [31:0] $end
$upscope $end
$upscope $end
$enddefinitions $end
#0
$dumpvars
bx [
bx Z
bx Y
bx X
bx W
0V
xU
bx T
bx S
bx R
bx Q
bx P
0O
b0 N
b0 M
b0 L
b0 K
bx J
bx I
bx H
bx G
bx F
bx E
bx D
bx C
bx B
xA
x@
bx ?
x>
bx =
bx <
bx ;
bx :
x9
z8
b0 7
b0 6
b0 5
04
b0 3
02
01
00
b0 /
0.
b0 -
0,
0+
bx *
x)
x(
x'
bx &
x%
bx $
bx #
x"
x!
$end
#5
b0 D
0!
0'
0"
b0 #
b0 ;
b0 S
b0 $
b0 <
b0 R
0(
0)
b0 *
b0 ?
b0 H
b0 P
b0 B
b0 C
b0 I
0@
0>
b0 F
09
b0 :
b0 E
b0 G
0A
1+
#10
0+
#15
1+
#20
0+
1,
#25
14
b10101100 3
b10101100 7
b10101100 M
10
b1000 /
b1000 6
b1000 L
1A
b10101100 [
b1000 Z
1+
#30
0+
#35
1>
1%
b0 &
b0 =
b0 Q
b10101100 T
1!
1'
1+
#40
0+
#45
04
00
1+
#50
0+
#55
0!
0'
11
1+
#60
0+
#65
14
b10100010 3
b10100010 7
b10100010 M
10
b1100 /
b1100 6
b1100 L
01
0%
b10100010 [
b1100 Z
1+
#70
0+
#75
1%
b10100010 W
1!
1'
1+
#80
0+
#85
04
00
1+
#90
0+
#95
0!
0'
11
1+
#100
0+
#105
14
b0 3
b0 7
b0 M
10
b100 /
b100 6
b100 L
01
0%
b0 [
b100 Z
1+
#110
0+
#115
1%
1!
1'
1+
#120
0+
#125
04
00
1+
#130
0+
#135
0!
0'
11
1+
#140
0+
#145
14
b1 3
b1 7
b1 M
10
b0 /
b0 6
b0 L
01
0%
b1 [
b0 Z
1+
#150
0+
#155
1O
b10101100 N
1%
1U
1!
1'
1+
#160
0+
#165
b101000110000000000110101100 J
04
00
b10101100 *
b10101100 ?
b10101100 H
b10101100 P
1)
1+
#170
0+
#175
1@
b101000110000000000110101100 B
b101000110000000000110101100 C
b101000110000000000110101100 I
0!
0'
11
1+
#180
0+
#185
b1 D
01
0%
0>
0@
b1 G
1+
#190
0+
#195
b1011000 N
1@
1>
1+
#200
0+
#205
b10000011000000000101011000 J
b10 D
b1011000 *
b1011000 ?
b1011000 H
b1011000 P
0>
0@
b10 G
1+
#210
0+
#215
b10110000 N
1@
b10000011000000000101011000 B
b10000011000000000101011000 C
b10000011000000000101011000 I
1>
1+
#220
0+
#225
b101000110000010001010110000 J
b11 D
b10110000 *
b10110000 ?
b10110000 H
b10110000 P
0>
0@
b11 G
1+
#230
0+
#235
b1100000 N
1@
b101000110000010001010110000 B
b101000110000010001010110000 C
b101000110000010001010110000 I
1>
1+
#240
0+
#245
b10000011000010001001100000 J
b100 D
b1100000 *
b1100000 ?
b1100000 H
b1100000 P
0>
0@
b100 G
1+
#250
0+
#255
b11000001 N
1@
b10000011000010001001100000 B
b10000011000010001001100000 C
b10000011000010001001100000 I
1>
1+
#260
0+
